pytestix/__init__.py
pytestix/cli.py
pytestix/config.py
pytestix/core.py
pytestix/scaffold.py
pytestix/driver/__init__.py
pytestix/driver/api.py
pytestix/driver/web.py
pytestix/test_project/api_test/__init__.py
pytestix/test_project/api_test/test_application/__init__.py
pytestix/test_project/api_test/test_application/http/__init__.py
pytestix/test_project/api_test/test_application/http/template/__init__.py
pytestix/test_project/api_test/test_application/http/template/body.py
pytestix/test_project/api_test/test_application/http/template/header.py
pytestix/test_project/api_test/test_application/http/template/interface.py
pytestix/test_project/api_test/test_application/http/template/url.py
pytestix/test_project/api_test/test_application/http/test_case/__init__.py
pytestix/test_project/api_test/test_application/http/test_case/busi.py
pytestix/test_project/api_test/test_application/http/test_case/flow.py
pytestix/test_project/api_test/test_application/http/test_case/interface.py
pytestix/test_project/api_test/test_application/http/test_case/prod.py
pytestix/test_project/api_test/test_application/http/test_data/__init__.py
pytestix/test_project/api_test/test_application/http/test_data/busi.py
pytestix/test_project/api_test/test_application/http/test_data/flow.py
pytestix/test_project/api_test/test_application/http/test_data/interface.py
pytestix/test_project/api_test/test_application/http/test_data/prod.py
pytestix/test_project/ui_test/__init__.py
pytestix/test_project/ui_test/test_application/__init__.py
pytestix/test_project/ui_test/test_application/locators/__init__.py
pytestix/test_project/ui_test/test_application/locators/test_locators.py
pytestix/test_project/ui_test/test_application/page_objects/__init__.py
pytestix/test_project/ui_test/test_application/page_objects/test_po.py
pytestix/test_project/ui_test/test_application/test_cases/__init__.py
pytestix/test_project/ui_test/test_application/test_cases/busi.py
pytestix-0.1.0.dist-info/LICENSE
pytestix-0.1.0.dist-info/METADATA
pytestix-0.1.0.dist-info/WHEEL
pytestix-0.1.0.dist-info/entry_points.txt
pytestix-0.1.0.dist-info/top_level.txt
pytestix-0.1.0.dist-info/RECORD
