Metadata-Version: 2.1
Name: pytestix
Version: 0.1.0
Summary: pytestix is a pytest-based automation testing framework for api, ui, app testing
Home-page: https://github.com/jaylu2018/pytestify
Author: luyh
Author-email: jaylu1995@outlook.com
License: Apache License 2.0
Platform: UNKNOWN
Classifier: Intended Audience :: Developers
Classifier: Operating System :: MacOS :: MacOS X
Classifier: Operating System :: Microsoft :: Windows
Classifier: Programming Language :: Python
Classifier: Programming Language :: Python :: 3.7
Classifier: Programming Language :: Python :: 3.8
Classifier: Programming Language :: Python :: 3.9
License-File: LICENSE
Requires-Dist: pytest (~=7.2.1)
Requires-Dist: playwright (~=1.30.0)
Requires-Dist: pytest-playwright (~=0.3.0)
Requires-Dist: httpx (~=0.23.3)
Requires-Dist: pytest-cases (~=3.6.13)
Requires-Dist: loguru (~=0.6.0)
Requires-Dist: prettytable (~=3.6.0)
